chatarena/__init__.py
chatarena/agent.py
chatarena/arena.py
chatarena/config.py
chatarena/database.py
chatarena/message.py
chatarena/pettingzoo_compatibility.py
chatarena/utils.py
chatarena/backends/__init__.py
chatarena/backends/anthropic.py
chatarena/backends/bard.py
chatarena/backends/base.py
chatarena/backends/cohere.py
chatarena/backends/hf_transformers.py
chatarena/backends/human.py
chatarena/backends/langchain.py
chatarena/backends/openai.py
chatarena/environments/__init__.py
chatarena/environments/base.py
chatarena/environments/chameleon.py
chatarena/environments/conversation.py
chatarena/environments/pettingzoo_chess.py
chatarena/environments/pettingzoo_tictactoe.py
chatarena/environments/umshini/__init__.py
chatarena/environments/umshini/base.py
chatarena/environments/umshini/content_moderation.py
chatarena/environments/umshini/debate.py
chatarena/environments/umshini/deception.py
chatarena/environments/umshini/pettingzoo_wrapper.py
chatarena/environments/umshini/symmetric_content_moderation.py
chatarena/environments/umshini/symmetric_deception.py
chatarena/environments/umshini/agents/__init__.py
chatarena/environments/umshini/agents/content_moderation_bots.py
chatarena/environments/umshini/agents/debate_bots.py
chatarena/environments/umshini/agents/deception_bots.py
chatarena/ui/__init__.py
chatarena/ui/cli.py
chatarena-0.1.18.dist-info/LICENSE
chatarena-0.1.18.dist-info/METADATA
chatarena-0.1.18.dist-info/WHEEL
chatarena-0.1.18.dist-info/top_level.txt
chatarena-0.1.18.dist-info/RECORD
