Metadata-Version: 2.1
Name: chatarena
Version: 0.1.18
Summary: Multi-Agent Language Game Environments for Large Language Models
Author-email: Yuxiang Wu <yuxiang.cs@gmail.com>
Project-URL: Homepage, https://github.com/chatarena/chatarena
Project-URL: Bug Tracker, https://github.com/chatarena/chatarena/issues
Classifier: Programming Language :: Python :: 3
Classifier: License :: OSI Approved :: MIT License
Classifier: Operating System :: OS Independent
Requires-Python: >=3.7
License-File: LICENSE
Requires-Dist: openai >=1.0.0
Requires-Dist: tenacity ==8.2.2
Requires-Dist: rich ==13.3.3
Requires-Dist: prompt-toolkit ==3.0.38
Provides-Extra: all
Requires-Dist: anthropic ==0.2.8 ; extra == 'all'
Requires-Dist: cohere ==4.3.1 ; extra == 'all'
Requires-Dist: transformers >=4.27.4 ; extra == 'all'
Requires-Dist: gradio ==3.34.0 ; extra == 'all'
Requires-Dist: pydantic ==1.10.13 ; extra == 'all'
Requires-Dist: pettingzoo >=1.24.0 ; extra == 'all'
Requires-Dist: chess ==1.9.4 ; extra == 'all'
Requires-Dist: rlcard ==1.0.5 ; extra == 'all'
Requires-Dist: pygame ==2.3.0 ; extra == 'all'
Requires-Dist: gymnasium >=0.28.1 ; extra == 'all'
Requires-Dist: colorama >=0.4.6 ; extra == 'all'
Requires-Dist: supabase ==2.0.3 ; extra == 'all'
Requires-Dist: bardapi ==0.1.11 ; extra == 'all'
Requires-Dist: langchain >=0.0.340 ; extra == 'all'
Requires-Dist: deptry >=0.12.0 ; extra == 'all'
Requires-Dist: pytest >=7.4.3 ; extra == 'all'
Requires-Dist: pytest-cov >=4.1.0 ; extra == 'all'
Requires-Dist: pytest-xdist >=3.4.0 ; extra == 'all'
Provides-Extra: all_backends
Requires-Dist: anthropic >=0.2.8 ; extra == 'all_backends'
Requires-Dist: cohere >=4.3.1 ; extra == 'all_backends'
Requires-Dist: transformers >=4.27.4 ; extra == 'all_backends'
Requires-Dist: bardapi ==0.1.11 ; extra == 'all_backends'
Requires-Dist: langchain >=0.0.135 ; extra == 'all_backends'
Provides-Extra: all_envs
Requires-Dist: pettingzoo >=1.24.0 ; extra == 'all_envs'
Requires-Dist: chess ==1.9.4 ; extra == 'all_envs'
Requires-Dist: rlcard ==1.0.5 ; extra == 'all_envs'
Requires-Dist: pygame ==2.3.0 ; extra == 'all_envs'
Requires-Dist: langchain >=0.0.135 ; extra == 'all_envs'
Provides-Extra: anthropic
Requires-Dist: anthropic <0.3.0,>=0.2.8 ; extra == 'anthropic'
Provides-Extra: bard
Requires-Dist: bardapi ==0.1.11 ; extra == 'bard'
Provides-Extra: cohere
Requires-Dist: cohere >=4.3.1 ; extra == 'cohere'
Provides-Extra: database
Requires-Dist: supabase ==2.0.3 ; extra == 'database'
Provides-Extra: gradio
Requires-Dist: gradio ==3.34.0 ; extra == 'gradio'
Requires-Dist: pydantic ==1.10.13 ; extra == 'gradio'
Provides-Extra: huggingface
Requires-Dist: transformers >=4.27.4 ; extra == 'huggingface'
Provides-Extra: langchain
Requires-Dist: langchain >=0.0.340 ; extra == 'langchain'
Provides-Extra: pettingzoo
Requires-Dist: pettingzoo >=1.24.0 ; extra == 'pettingzoo'
Requires-Dist: chess ==1.9.4 ; extra == 'pettingzoo'
Requires-Dist: rlcard ==1.0.5 ; extra == 'pettingzoo'
Requires-Dist: pygame ==2.3.0 ; extra == 'pettingzoo'
Requires-Dist: gymnasium >=0.28.1 ; extra == 'pettingzoo'
Provides-Extra: testing
Requires-Dist: deptry >=0.12.0 ; extra == 'testing'
Requires-Dist: pytest >=7.4.3 ; extra == 'testing'
Requires-Dist: pytest-cov >=4.1.0 ; extra == 'testing'
Requires-Dist: pytest-xdist >=3.4.0 ; extra == 'testing'
Provides-Extra: umshini
Requires-Dist: pettingzoo >=1.24.1 ; extra == 'umshini'
Requires-Dist: chess ==1.9.4 ; extra == 'umshini'
Requires-Dist: rlcard ==1.0.5 ; extra == 'umshini'
Requires-Dist: pygame ==2.3.0 ; extra == 'umshini'
Requires-Dist: gymnasium >=0.28.1 ; extra == 'umshini'
Requires-Dist: langchain >=0.0.340 ; extra == 'umshini'
Requires-Dist: colorama >=0.4.6 ; extra == 'umshini'
